pyperspace/__init__.py
pyperspace/__main__.py
pyperspace/config.py
pyperspace/rest_api.py
pyperspace/daemon/__init__.py
pyperspace/daemon/daemon.py
pyperspace/daemon/dataset.py
pyperspace/data/__init__.py
pyperspace/data/count.py
pyperspace/data/entry.py
pyperspace/data/interval.py
pyperspace/data/map.py
pyperspace/data/tree.py
pyperspace/io/__init__.py
pyperspace/io/cfile.py
pyperspace/io/fd.py
pyperspace/io/file.py
pyperspace/io/mmap_file.py
pyperspace/io/ring_buffer.py
pyperspace/io/wal.py
pyperspace/networking/__init__.py
pyperspace/networking/reactive.py
pyperspace/networking/socket.py
pyperspace/protocol/__init__.py
pyperspace/protocol/dataset_ipc.py
pyperspace/protocol/node.py
pyperspace/protocol/node_pb2.py
pyperspace/protocol/storage.py
pyperspace/protocol/storage_pb2.py
pyperspace/storage/__init__.py
pyperspace/storage/convert.py
pyperspace/storage/dataset.py
pyperspace/storage/deletion.py
pyperspace/storage/lsm.py
pyperspace/storage/lsm_dataset.py
pyperspace/storage/memtable.py
pyperspace/storage/select.py
pyperspace/storage/storage_mgr.py
pyperspace/workers/__init__.py
pyperspace/workers/dataset.py
pyperspace/workers/node.py
pyperspace/workers/storage.py
pyperspace-0.1.14.data/data/config/sample.yaml
tools/__init__.py
tools/lsm_check.py
tools/lsm_merge.py
tools/lsm_reader.py
tools/lsm_stat.py
tools/wal2lsm.py
tools/wal_reader.py
pyperspace-0.1.14.dist-info/METADATA
pyperspace-0.1.14.dist-info/WHEEL
pyperspace-0.1.14.dist-info/entry_points.txt
pyperspace-0.1.14.dist-info/top_level.txt
pyperspace-0.1.14.dist-info/RECORD
