Metadata-Version: 2.1
Name: pyperspace
Version: 0.1.14
Summary: Time series database server
Home-page: https://www.nuradius.com
Author: Nuradius Software
Author-email: todd@datacomponents.net
License: Apache Software License
Platform: UNKNOWN
Classifier: Development Status :: 3 - Alpha
Classifier: Intended Audience :: Developers
Classifier: License :: OSI Approved :: Apache Software License
Classifier: Programming Language :: Python
Classifier: Programming Language :: Python :: 3
Classifier: Programming Language :: Python :: 3.7
Classifier: Programming Language :: Python :: 3.8
Classifier: Programming Language :: Python :: 3.9
Requires-Python: >=3.7
Requires-Dist: fastapi (==0.79.0)
Requires-Dist: protobuf (==3.20.0)
Requires-Dist: PyYAML (==5.3.1)
Requires-Dist: ujson (==5.2.0)
Requires-Dist: uvicorn (==0.18.2)
